fetchomatic/__init__.py
fetchomatic/core.py
fetchomatic/exceptions.py
fetchomatic/http_client.py
fetchomatic/middleware.py
fetchomatic/protocols.py
fetchomatic/udp_client.py
fetchomatic/utils.py
fetchomatic/websocket_client.py
fetchomatic-1.0.0.dist-info/licenses/LICENSE
fetchomatic-1.0.0.dist-info/METADATA
fetchomatic-1.0.0.dist-info/WHEEL
fetchomatic-1.0.0.dist-info/entry_points.txt
fetchomatic-1.0.0.dist-info/top_level.txt
fetchomatic-1.0.0.dist-info/RECORD
