Metadata-Version: 2.4
Name: fetchomatic
Version: 1.0.0
Summary: A comprehensive networking framework with semantic methods
Home-page: https://github.com/Aayushbohora/smartfetchpy
Author: Aayush Bohora
Author-email: Aayush Bohora <ab6203200@gmail.com>
License: MIT
Project-URL: Homepage, https://github.com/Aayushbohora/smartfetchpy
Project-URL: Bug Reports, https://github.com/Aayushbohora/smartfetchpy/issues
Project-URL: Source, https://github.com/Aayushbohora/smartfetchpy
Classifier: Development Status :: 5 - Production/Stable
Classifier: Intended Audience :: Developers
Classifier: License :: OSI Approved :: MIT License
Classifier: Programming Language :: Python :: 3
Classifier: Programming Language :: Python :: 3.7
Classifier: Programming Language :: Python :: 3.8
Classifier: Programming Language :: Python :: 3.9
Classifier: Programming Language :: Python :: 3.10
Classifier: Programming Language :: Python :: 3.11
Requires-Python: >=3.7
License-File: LICENSE
Requires-Dist: requests>=2.25.0
Requires-Dist: aiohttp>=3.7.0
Requires-Dist: websockets>=10.0
Requires-Dist: PyYAML>=5.4.0
Provides-Extra: dev
Requires-Dist: pytest>=6.0; extra == "dev"
Requires-Dist: pytest-asyncio>=0.18.0; extra == "dev"
Requires-Dist: black>=21.0.0; extra == "dev"
Requires-Dist: isort>=5.0.0; extra == "dev"
Requires-Dist: mypy>=0.900; extra == "dev"
Dynamic: license-file
